LICENSE.md
MANIFEST.in
README.md
setup.py
docums_awesome_pages_plugin/__init__.py
docums_awesome_pages_plugin/meta.py
docums_awesome_pages_plugin/navigation.py
docums_awesome_pages_plugin/options.py
docums_awesome_pages_plugin/plugin.py
docums_awesome_pages_plugin/utils.py
docums_awesome_pages_plugin.egg-info/PKG-INFO
docums_awesome_pages_plugin.egg-info/SOURCES.txt
docums_awesome_pages_plugin.egg-info/dependency_links.txt
docums_awesome_pages_plugin.egg-info/entry_points.txt
docums_awesome_pages_plugin.egg-info/requires.txt
docums_awesome_pages_plugin.egg-info/top_level.txt