Metadata-Version: 1.2
Name: docums-awesome-pages-plugin
Version: 2.6.1
Summary: An Docums plugin that simplifies configuring page titles and their order
Home-page: https://github.com/khanhduy1407/docums-awesome-pages-plugin/
Author: NKDuy
Author-email: kn145660@gmail.com
License: MIT
Keywords: docums python markdown wiki
Platform: UNKNOWN
Classifier: Development Status :: 5 - Production/Stable
Classifier: Intended Audience :: Developers
Classifier: Intended Audience :: Information Technology
Classifier: License :: OSI Approved :: MIT License
Classifier: Programming Language :: Python
Classifier: Programming Language :: Python :: 3 :: Only
Classifier: Programming Language :: Python :: 3.5
Classifier: Programming Language :: Python :: 3.6
Classifier: Programming Language :: Python :: 3.7
Requires-Python: >=3.5
